{
  "allvideos": [
    {
      "caption": "Manjumel Boys",
      "url": "https://www.youtube.com/embed/id848Ww1YLo?si=QbmJIvTR-z6UL_ex&autoplay=1",
      "image": "https://media.licdn.com/dms/image/D4D12AQFLbkKRvDq3AQ/article-cover_image-shrink_600_2000/0/1709332270255?e=2147483647&v=beta&t=8AEXlDhQTl8FHBWdesLSQ7xMH4SFvxgh-BjhmBAcKzU",
      "id": 18
    },
    {
      "caption": "Bramayugam",
      "url": "https://www.youtube.com/embed/7FLxInubR5Q?si=QbmJIvTR-z6UL_ex&autoplay=1",
      "image": "https://i.ytimg.com/vi/55pzldrBRJM/maxresdefault.jpg",
      "id": 19
    },
    {
      "caption": "Lucifer",
      "url": "https://www.youtube.com/embed/x1-Ya0NZQso?si=QbmJIvTR-z6UL_ex&autoplay=1",
      "image": "https://i.ytimg.com/vi/x1-Ya0NZQso/maxresdefault.jpg",
      "id": 20
    }
  ],
  "category": [
    {
      "name": "music",
      "videos": [
        {
          "caption": "Manjumel Boys",
          "url": "https://www.youtube.com/embed/id848Ww1YLo?si=QbmJIvTR-z6UL_ex&autoplay=1",
          "image": "https://media.licdn.com/dms/image/D4D12AQFLbkKRvDq3AQ/article-cover_image-shrink_600_2000/0/1709332270255?e=2147483647&v=beta&t=8AEXlDhQTl8FHBWdesLSQ7xMH4SFvxgh-BjhmBAcKzU",
          "id": 18
        },
        {
          "caption": "Lucifer",
          "url": "https://www.youtube.com/embed/x1-Ya0NZQso?si=QbmJIvTR-z6UL_ex&autoplay=1",
          "image": "https://i.ytimg.com/vi/x1-Ya0NZQso/maxresdefault.jpg",
          "id": 20
        }
      ],
      "id": 1
    },
    {
      "name": "Trailer",
      "videos": [
        {
          "caption": "Lucifer",
          "url": "https://www.youtube.com/embed/x1-Ya0NZQso?si=QbmJIvTR-z6UL_ex&autoplay=1",
          "image": "https://i.ytimg.com/vi/x1-Ya0NZQso/maxresdefault.jpg",
          "id": 20
        }
      ],
      "id": 2
    },
    {
      "name": "movies",
      "videos": [
        {
          "caption": "Bramayugam",
          "url": "https://www.youtube.com/embed/7FLxInubR5Q?si=QbmJIvTR-z6UL_ex&autoplay=1",
          "image": "https://i.ytimg.com/vi/55pzldrBRJM/maxresdefault.jpg",
          "id": 19
        }
      ],
      "id": 3
    }
  ],
  "history": [
    {
      "caption": "Manjumel Boys",
      "url": "https://www.youtube.com/embed/id848Ww1YLo?si=QbmJIvTR-z6UL_ex&autoplay=1",
      "datetime": "2024-03-12T05:31:35.200Z",
      "id": 2
    },
    {
      "caption": "Manjumel Boys",
      "url": "https://www.youtube.com/embed/id848Ww1YLo?si=QbmJIvTR-z6UL_ex&autoplay=1",
      "datetime": "2024-03-12T05:32:23.705Z",
      "id": 3
    },
    {
      "caption": "Bramayugam",
      "url": "https://www.youtube.com/embed/7FLxInubR5Q?si=QbmJIvTR-z6UL_ex&autoplay=1",
      "datetime": "2024-03-12T05:32:26.856Z",
      "id": 4
    },
    {
      "caption": "Lucifer",
      "url": "https://www.youtube.com/embed/x1-Ya0NZQso?si=QbmJIvTR-z6UL_ex&autoplay=1",
      "datetime": "2024-03-12T05:32:29.511Z",
      "id": 5
    },
    {
      "caption": "Manjumel Boys",
      "url": "https://www.youtube.com/embed/id848Ww1YLo?si=QbmJIvTR-z6UL_ex&autoplay=1",
      "datetime": "2024-03-12T05:32:32.196Z",
      "id": 6
    },
    {
      "caption": "Bramayugam",
      "url": "https://www.youtube.com/embed/7FLxInubR5Q?si=QbmJIvTR-z6UL_ex&autoplay=1",
      "datetime": "2024-03-12T05:32:34.826Z",
      "id": 7
    },
    {
      "caption": "Lucifer",
      "url": "https://www.youtube.com/embed/x1-Ya0NZQso?si=QbmJIvTR-z6UL_ex&autoplay=1",
      "datetime": "2024-03-12T06:20:04.488Z",
      "id": 8
    },
    {
      "caption": "Lucifer",
      "url": "https://www.youtube.com/embed/x1-Ya0NZQso?si=QbmJIvTR-z6UL_ex&autoplay=1",
      "datetime": "2024-03-13T05:08:02.022Z",
      "id": 9
    },
    {
      "caption": "Bramayugam",
      "url": "https://www.youtube.com/embed/7FLxInubR5Q?si=QbmJIvTR-z6UL_ex&autoplay=1",
      "datetime": "2024-03-13T05:08:13.175Z",
      "id": 10
    }
  ]
}